vercelpy/__init__.py
vercelpy/blob_store/__init__.py
vercelpy/edge_config/__init__.py
vercelpy/edge_config/connection.py
vercelpy/edge_config/edge.py
vercelpy/edge_config/errors.py
vercelpy-0.2.1.dist-info/LICENSE
vercelpy-0.2.1.dist-info/METADATA
vercelpy-0.2.1.dist-info/WHEEL
vercelpy-0.2.1.dist-info/RECORD
